SOM_TUI/landing.tcss
SOM_TUI/layout.tcss
SOM_TUI/main.py
SOM_TUI/runny.py
SOM_TUI/tui.py
som_tui-4.7.dist-info/licenses/LICENSE
som_tui-4.7.dist-info/METADATA
som_tui-4.7.dist-info/WHEEL
som_tui-4.7.dist-info/entry_points.txt
som_tui-4.7.dist-info/top_level.txt
som_tui-4.7.dist-info/RECORD
