Metadata-Version: 2.4
Name: SOM-TUI
Version: 4.7
Summary: A TUI that lets you vote on SOM project through the terminal!
Author-email: Yuva Nag <shreeyuva2020@gmail.com>
License-Expression: MIT
Project-URL: homepage, https://github.com/shreeyuvan2020/SOM-TUI
Project-URL: repository, https://github.com/shreeyuvan2020/SOM-TUI/issues
Classifier: Programming Language :: Python :: 3
Classifier: Operating System :: OS Independent
Requires-Python: >=3.9
License-File: LICENSE
Requires-Dist: requests==2.32.4
Requires-Dist: selenium==4.33.0
Requires-Dist: beautifulsoup4==4.13.4
Requires-Dist: webdriver_manager==4.0.1
Requires-Dist: textual==4.0.0
Requires-Dist: rich-pixels==3.0.1
Requires-Dist: requests==2.32.4
Requires-Dist: pillow==11.3.0
Requires-Dist: mpv==1.0.8
Dynamic: license-file
